OsziAPI/Agent.py
OsziAPI/Benchmark.py
OsziAPI/Country.py
OsziAPI/Currency.py
OsziAPI/DataLandscape.py
OsziAPI/DatabaseAPI.py
OsziAPI/Fund.py
OsziAPI/Helper.py
OsziAPI/Market.py
OsziAPI/Portfolio.py
OsziAPI/Position.py
OsziAPI/Returns.py
OsziAPI/Security.py
OsziAPI/Ticker.py
OsziAPI/__init__.py
OsziAPI/db_connection.py
OsziAPI-0.1.7.dist-info/METADATA
OsziAPI-0.1.7.dist-info/WHEEL
OsziAPI-0.1.7.dist-info/top_level.txt
OsziAPI-0.1.7.dist-info/RECORD
