Metadata-Version: 2.1
Name: OsziAPI
Version: 0.1.7
Summary: database api
Home-page: https://github.com/clresonanz/OsziAPI
Author: Liu Chang
Author-email: chang.liu@resonanzcapital.com
License: MIT License
Platform: any
